magellanmapper-1.7a1.dist-info/licenses/LICENSE.txt
magmap/__init__.py
magmap/atlas/__init__.py
magmap/atlas/atlas_refiner.py
magmap/atlas/edge_seg.py
magmap/atlas/labels_meta.py
magmap/atlas/ontology.py
magmap/atlas/reg_tasks.py
magmap/atlas/register.py
magmap/atlas/transformer.py
magmap/brain_globe/__init__.py
magmap/brain_globe/bg_controller.py
magmap/brain_globe/bg_model.py
magmap/cloud/__init__.py
magmap/cloud/aws.py
magmap/cloud/notify.py
magmap/cv/__init__.py
magmap/cv/chunking.py
magmap/cv/classifier.py
magmap/cv/colocalizer.py
magmap/cv/cv_nd.py
magmap/cv/detector.py
magmap/cv/segmenter.py
magmap/cv/stack_detect.py
magmap/cv/verifier.py
magmap/gui/__init__.py
magmap/gui/atlas_editor.py
magmap/gui/atlas_threads.py
magmap/gui/event_handlers.py
magmap/gui/image_viewer.py
magmap/gui/import_threads.py
magmap/gui/pixel_display.py
magmap/gui/plot_editor.py
magmap/gui/roi_editor.py
magmap/gui/verifier_editor.py
magmap/gui/vis_3d.py
magmap/gui/vis_handler.py
magmap/gui/visualizer.py
magmap/io/__init__.py
magmap/io/cli.py
magmap/io/df_io.py
magmap/io/export_regions.py
magmap/io/export_rois.py
magmap/io/export_stack.py
magmap/io/importer.py
magmap/io/libmag.py
magmap/io/load_env.py
magmap/io/naming.py
magmap/io/np_io.py
magmap/io/packaging.py
magmap/io/sitk_io.py
magmap/io/sqlite.py
magmap/io/subproc_io.py
magmap/io/yaml_io.py
magmap/plot/__init__.py
magmap/plot/colormaps.py
magmap/plot/plot_2d.py
magmap/plot/plot_3d.py
magmap/plot/plot_support.py
magmap/settings/__init__.py
magmap/settings/atlas_prof.py
magmap/settings/config.py
magmap/settings/grid_search_prof.py
magmap/settings/logs.py
magmap/settings/prefs_prof.py
magmap/settings/profiles.py
magmap/settings/roi_prof.py
magmap/stats/__init__.py
magmap/stats/atlas_stats.py
magmap/stats/clustering.py
magmap/stats/mlearn.py
magmap/stats/vols.py
magmap/tests/__init__.py
magmap/tests/test_chunking.py
magmap/tests/test_classifier.py
magmap/tests/test_cv_nd.py
magmap/tests/test_detector.py
magmap/tests/test_image_stack_integration.py
magmap/tests/test_img_equality.py
magellanmapper-1.7a1.dist-info/METADATA
magellanmapper-1.7a1.dist-info/WHEEL
magellanmapper-1.7a1.dist-info/entry_points.txt
magellanmapper-1.7a1.dist-info/top_level.txt
magellanmapper-1.7a1.dist-info/RECORD
