Metadata-Version: 2.4
Name: magellanmapper
Version: 1.7a1
Summary: 3D atlas analysis and annotation
Author-email: David Young <david@textflex.com>
Project-URL: Homepage, https://github.com/sanderslab/magellanmapper
Requires-Python: >=3.10
License-File: LICENSE.txt
Requires-Dist: scikit-image
Requires-Dist: matplotlib!=3.3.0,!=3.3.1
Requires-Dist: pandas
Requires-Dist: PyYAML
Requires-Dist: appdirs
Requires-Dist: importlib-metadata>=1.0; python_version < "3.8"
Requires-Dist: tifffile
Requires-Dist: imagecodecs
Requires-Dist: dataclasses; python_version < "3.7"
Requires-Dist: brainglobe-atlasapi; python_version >= "3.9"
Requires-Dist: bg-atlasapi; python_version < "3.9"
Requires-Dist: typing_extensions
Provides-Extra: import
Requires-Dist: javabridge==1.0.19.post4+gbebed64; python_version < "3.8" and extra == "import"
Requires-Dist: javabridge==1.0.19.post9+gc8c12b4; python_version >= "3.8" and extra == "import"
Requires-Dist: python-bioformats==4.0.5.post2+g51eb88a; python_version < "3.8" and extra == "import"
Requires-Dist: python-bioformats==4.0.7.post5+g52309d1; python_version >= "3.8" and extra == "import"
Provides-Extra: aws
Requires-Dist: boto3; extra == "aws"
Requires-Dist: awscli; extra == "aws"
Provides-Extra: pandas-plus
Requires-Dist: openpyxl; extra == "pandas-plus"
Requires-Dist: jinja2; extra == "pandas-plus"
Provides-Extra: docs
Requires-Dist: sphinx; extra == "docs"
Requires-Dist: sphinx-autodoc-typehints; extra == "docs"
Requires-Dist: myst-parser; extra == "docs"
Requires-Dist: furo; extra == "docs"
Provides-Extra: jupyter
Requires-Dist: jupyterlab; extra == "jupyter"
Requires-Dist: bash_kernel; extra == "jupyter"
Provides-Extra: classifier
Requires-Dist: tensorflow; extra == "classifier"
Provides-Extra: gui
Requires-Dist: PyQt5!=5.15.8; extra == "gui"
Requires-Dist: pyface; extra == "gui"
Requires-Dist: traitsui; extra == "gui"
Provides-Extra: 3d
Requires-Dist: mayavi; extra == "3d"
Requires-Dist: vtk<9.3.0; extra == "3d"
Provides-Extra: itk
Requires-Dist: itk-elastix==0.20; extra == "itk"
Provides-Extra: simplitk
Requires-Dist: simpleitk==2.0.2rc2.dev785+g8ac4f; python_version < "3.8" and extra == "simplitk"
Requires-Dist: simpleitk==2.3.0.dev117+g0640d; python_version >= "3.8" and extra == "simplitk"
Provides-Extra: most
Requires-Dist: matplotlib_scalebar; extra == "most"
Requires-Dist: pyamg; extra == "most"
Requires-Dist: magellanmapper[gui]; extra == "most"
Requires-Dist: magellanmapper[itk]; extra == "most"
Provides-Extra: all
Requires-Dist: matplotlib_scalebar; extra == "all"
Requires-Dist: pyamg; extra == "all"
Requires-Dist: seaborn; extra == "all"
Requires-Dist: scikit-learn; extra == "all"
Requires-Dist: magellanmapper[gui]; extra == "all"
Requires-Dist: magellanmapper[docs]; extra == "all"
Requires-Dist: magellanmapper[itk]; extra == "all"
Requires-Dist: magellanmapper[import]; extra == "all"
Requires-Dist: magellanmapper[aws]; extra == "all"
Requires-Dist: magellanmapper[jupyter]; extra == "all"
Requires-Dist: magellanmapper[3d]; extra == "all"
Dynamic: license-file
